GooseSLURM/__init__.py
GooseSLURM/_version.py
GooseSLURM/cli_Gdel.py
GooseSLURM/cli_Ginfo.py
GooseSLURM/cli_Gps.py
GooseSLURM/cli_Gstat.py
GooseSLURM/cli_Gsub.py
GooseSLURM/duration.py
GooseSLURM/fileio.py
GooseSLURM/files.py
GooseSLURM/memory.py
GooseSLURM/output.py
GooseSLURM/ps.py
GooseSLURM/rich.py
GooseSLURM/sacct.py
GooseSLURM/scripts.py
GooseSLURM/sinfo.py
GooseSLURM/squeue.py
GooseSLURM/table.py
GooseSLURM-0.13.4.dist-info/LICENSE
GooseSLURM-0.13.4.dist-info/METADATA
GooseSLURM-0.13.4.dist-info/WHEEL
GooseSLURM-0.13.4.dist-info/entry_points.txt
GooseSLURM-0.13.4.dist-info/top_level.txt
GooseSLURM-0.13.4.dist-info/RECORD
