Metadata-Version: 2.1
Name: GooseSLURM
Version: 0.13.4
Summary: Support functions for SLURM
Author-email: Tom de Geus <tom@geus.me>
Project-URL: Source, https://github.com/tdegeus/GooseSLURM
Classifier: License :: OSI Approved :: MIT License
Requires-Python: >=3.6
License-File: LICENSE
Requires-Dist: numpy
Requires-Dist: click
Requires-Dist: tqdm
Requires-Dist: PyYAML
